<?xml version="1.0" encoding="UTF-8" standalone="yes"?>
<circuitDetailss>
    <DATA_DS>
        <PRM_CID></PRM_CID>
        <PRM_TID>WRRNOHCB1ZW</PRM_TID>
        <CIRCUIT_ID>33.L1XX.004115..TWCC</CIRCUIT_ID>
        <REVISION></REVISION>
        <CIRCUIT_STATUS>Live</CIRCUIT_STATUS>
        <BANDWIDTH>100 Mbps</BANDWIDTH>
        <CATEGORY>ETHERNET</CATEGORY>
        <A_SIDE_SITE>CLMBOHNJ-SOO-THE OHIO STATE UNIVERSITY/NR1/1320 ARTHUR E ADAMS DR</A_SIDE_SITE>
        <Z_SIDE_SITE>WRRNOHCB_STATE OF OHIO/TRUMBULL/280 N PARK AVE</Z_SIDE_SITE>
        <UTILIZATION></UTILIZATION>
        <BPS_ALLOCATED></BPS_ALLOCATED>
        <IN_SERVICE></IN_SERVICE>
        <Z_CUSTOMER_NAME></Z_CUSTOMER_NAME>
        <TOPOLOGY></TOPOLOGY>
        <ORDERING_CUSTOMER>STATE OF OHIO</ORDERING_CUSTOMER>
        <ADDRESS></ADDRESS>
        <CITY></CITY>
        <STATE></STATE>
        <A_ADDRESS>1320 ARTHUR E ADAMS DR</A_ADDRESS>
        <A_CITY>COLUMBUS</A_CITY>
        <A_STATE>OH</A_STATE>
        <REPORT_DATE></REPORT_DATE>
        <TID>WRRNOHCB1ZW</TID>
        <LASTMODIFYDATE></LASTMODIFYDATE>
        <LEGACY_CKT_ID></LEGACY_CKT_ID>
        <TSP></TSP>
        <A_SIDE_CUSTOMER>SOO - DEPT JFS</A_SIDE_CUSTOMER>
        <Z_SIDE_CUSTOMER>SOO - DEPT JFS</Z_SIDE_CUSTOMER>
        <SERVICE_TYPE>COM-EVPL</SERVICE_TYPE>
        <CUSTOMER_PROVIDED_VLAN></CUSTOMER_PROVIDED_VLAN>
        <A_SITE_TYPE>LOCAL</A_SITE_TYPE>
        <Z_SITE_TYPE>LOCAL</Z_SITE_TYPE>
        <A_SITE_ID></A_SITE_ID>
        <Z_SITE_ID></Z_SITE_ID>
        <A_SITE_ADDRESS></A_SITE_ADDRESS>
        <Z_SITE_ADDRESS></Z_SITE_ADDRESS>
    </DATA_DS>
    <DATA_DS>
        <PRM_CID></PRM_CID>
        <PRM_TID>WRRNOHCB1ZW</PRM_TID>
        <CIRCUIT_ID>33.L1XX.005437..TWCC</CIRCUIT_ID>
        <REVISION></REVISION>
        <CIRCUIT_STATUS>Live</CIRCUIT_STATUS>
        <BANDWIDTH>25 Mbps</BANDWIDTH>
        <CATEGORY>ETHERNET</CATEGORY>
        <A_SIDE_SITE>WRRNOH55_TWC/HUB W1-NILES RD</A_SIDE_SITE>
        <Z_SIDE_SITE>WRRNOHCB_STATE OF OHIO/TRUMBULL/280 N PARK AVE</Z_SIDE_SITE>
        <UTILIZATION></UTILIZATION>
        <BPS_ALLOCATED></BPS_ALLOCATED>
        <IN_SERVICE></IN_SERVICE>
        <Z_CUSTOMER_NAME></Z_CUSTOMER_NAME>
        <TOPOLOGY></TOPOLOGY>
        <ORDERING_CUSTOMER>TRUMBULL COUNTY JOB AND FAMILY SERVICES</ORDERING_CUSTOMER>
        <ADDRESS></ADDRESS>
        <CITY></CITY>
        <STATE></STATE>
        <A_ADDRESS>3775 NILES RD SE</A_ADDRESS>
        <A_CITY>WARREN</A_CITY>
        <A_STATE>OH</A_STATE>
        <REPORT_DATE></REPORT_DATE>
        <TID>WRRNOHCB1ZW</TID>
        <LASTMODIFYDATE></LASTMODIFYDATE>
        <LEGACY_CKT_ID></LEGACY_CKT_ID>
        <TSP></TSP>
        <A_SIDE_CUSTOMER></A_SIDE_CUSTOMER>
        <Z_SIDE_CUSTOMER>TRUMBULL COUNTY JOB AND FAMILY SERVICES</Z_SIDE_CUSTOMER>
        <SERVICE_TYPE>COM-DIA</SERVICE_TYPE>
        <CUSTOMER_PROVIDED_VLAN></CUSTOMER_PROVIDED_VLAN>
        <A_SITE_TYPE>HUB</A_SITE_TYPE>
        <Z_SITE_TYPE>LOCAL</Z_SITE_TYPE>
        <A_SITE_ID>HUB W1-NILES RD</A_SITE_ID>
        <Z_SITE_ID></Z_SITE_ID>
        <A_SITE_ADDRESS></A_SITE_ADDRESS>
        <Z_SITE_ADDRESS></Z_SITE_ADDRESS>
    </DATA_DS>
    <DATA_DS>
        <PRM_CID></PRM_CID>
        <PRM_TID>WRRNOHCB1ZW</PRM_TID>
        <CIRCUIT_ID>41001.GE1.WRRNOHCB1ZW.WRRNOHCB1ZW</CIRCUIT_ID>
        <REVISION></REVISION>
        <CIRCUIT_STATUS>Live</CIRCUIT_STATUS>
        <BANDWIDTH>1 Gbps</BANDWIDTH>
        <CATEGORY>ETHERNET TRANSPORT</CATEGORY>
        <A_SIDE_SITE>WRRNOHCB_STATE OF OHIO/TRUMBULL/280 N PARK AVE</A_SIDE_SITE>
        <Z_SIDE_SITE>WRRNOHCB_STATE OF OHIO/TRUMBULL/280 N PARK AVE</Z_SIDE_SITE>
        <UTILIZATION></UTILIZATION>
        <BPS_ALLOCATED></BPS_ALLOCATED>
        <IN_SERVICE></IN_SERVICE>
        <Z_CUSTOMER_NAME></Z_CUSTOMER_NAME>
        <TOPOLOGY></TOPOLOGY>
        <ORDERING_CUSTOMER>STATE OF OHIO</ORDERING_CUSTOMER>
        <ADDRESS></ADDRESS>
        <CITY></CITY>
        <STATE></STATE>
        <A_ADDRESS>280 N PARK AVE</A_ADDRESS>
        <A_CITY>WARREN</A_CITY>
        <A_STATE>OH</A_STATE>
        <REPORT_DATE></REPORT_DATE>
        <TID>WRRNOHCB1ZW</TID>
        <LASTMODIFYDATE></LASTMODIFYDATE>
        <LEGACY_CKT_ID></LEGACY_CKT_ID>
        <TSP></TSP>
        <A_SIDE_CUSTOMER>STATE OF OHIO</A_SIDE_CUSTOMER>
        <Z_SIDE_CUSTOMER>STATE OF OHIO</Z_SIDE_CUSTOMER>
        <SERVICE_TYPE>COM-CUSTOMER TRANSPORT</SERVICE_TYPE>
        <CUSTOMER_PROVIDED_VLAN></CUSTOMER_PROVIDED_VLAN>
        <A_SITE_TYPE>LOCAL</A_SITE_TYPE>
        <Z_SITE_TYPE>LOCAL</Z_SITE_TYPE>
        <A_SITE_ID></A_SITE_ID>
        <Z_SITE_ID></Z_SITE_ID>
        <A_SITE_ADDRESS></A_SITE_ADDRESS>
        <Z_SITE_ADDRESS></Z_SITE_ADDRESS>
    </DATA_DS>
    <DATA_DS>
        <PRM_CID></PRM_CID>
        <PRM_TID>WRRNOHCB1ZW</PRM_TID>
        <CIRCUIT_ID>61.L1XX.000005.211.TWCC</CIRCUIT_ID>
        <REVISION></REVISION>
        <CIRCUIT_STATUS>Live</CIRCUIT_STATUS>
        <BANDWIDTH>100 Mbps</BANDWIDTH>
        <CATEGORY>ETHERNET</CATEGORY>
        <A_SIDE_SITE>CLMBOHNJ-SOO-THE OHIO STATE UNIVERSITY/NR1/1320 ARTHUR E ADAMS DR</A_SIDE_SITE>
        <Z_SIDE_SITE>WRRNOHCB_STATE OF OHIO/TRUMBULL/280 N PARK AVE</Z_SIDE_SITE>
        <UTILIZATION></UTILIZATION>
        <BPS_ALLOCATED></BPS_ALLOCATED>
        <IN_SERVICE></IN_SERVICE>
        <Z_CUSTOMER_NAME></Z_CUSTOMER_NAME>
        <TOPOLOGY></TOPOLOGY>
        <ORDERING_CUSTOMER>STATE OF OHIO</ORDERING_CUSTOMER>
        <ADDRESS></ADDRESS>
        <CITY></CITY>
        <STATE></STATE>
        <A_ADDRESS>1320 ARTHUR E ADAMS DR</A_ADDRESS>
        <A_CITY>COLUMBUS</A_CITY>
        <A_STATE>OH</A_STATE>
        <REPORT_DATE></REPORT_DATE>
        <TID>WRRNOHCB1ZW</TID>
        <LASTMODIFYDATE></LASTMODIFYDATE>
        <LEGACY_CKT_ID></LEGACY_CKT_ID>
        <TSP></TSP>
        <A_SIDE_CUSTOMER>STATE OF OHIO</A_SIDE_CUSTOMER>
        <Z_SIDE_CUSTOMER>STATE OF OHIO</Z_SIDE_CUSTOMER>
        <SERVICE_TYPE>COM-EVPL</SERVICE_TYPE>
        <CUSTOMER_PROVIDED_VLAN>3391</CUSTOMER_PROVIDED_VLAN>
        <A_SITE_TYPE>LOCAL</A_SITE_TYPE>
        <Z_SITE_TYPE>LOCAL</Z_SITE_TYPE>
        <A_SITE_ID></A_SITE_ID>
        <Z_SITE_ID></Z_SITE_ID>
        <A_SITE_ADDRESS></A_SITE_ADDRESS>
        <Z_SITE_ADDRESS></Z_SITE_ADDRESS>
    </DATA_DS>
    <DATA_DS>
        <PRM_CID></PRM_CID>
        <PRM_TID>WRRNOHCB1ZW</PRM_TID>
        <CIRCUIT_ID>33.L1XX.000006.210.TWCC</CIRCUIT_ID>
        <REVISION></REVISION>
        <CIRCUIT_STATUS>Live</CIRCUIT_STATUS>
        <BANDWIDTH>100 Mbps</BANDWIDTH>
        <CATEGORY>ETHERNET</CATEGORY>
        <A_SIDE_SITE>WRRNOHCB_STATE OF OHIO/TRUMBULL/280 N PARK AVE</A_SIDE_SITE>
        <Z_SIDE_SITE>CMBROHXF_SOO DEPT JFS//324 HIGHLAND AVE</Z_SIDE_SITE>
        <UTILIZATION></UTILIZATION>
        <BPS_ALLOCATED></BPS_ALLOCATED>
        <IN_SERVICE></IN_SERVICE>
        <Z_CUSTOMER_NAME></Z_CUSTOMER_NAME>
        <TOPOLOGY></TOPOLOGY>
        <ORDERING_CUSTOMER>STATE OF OHIO</ORDERING_CUSTOMER>
        <ADDRESS></ADDRESS>
        <CITY></CITY>
        <STATE></STATE>
        <A_ADDRESS>280 N PARK AVE</A_ADDRESS>
        <A_CITY>WARREN</A_CITY>
        <A_STATE>OH</A_STATE>
        <REPORT_DATE></REPORT_DATE>
        <TID>WRRNOHCB1ZW</TID>
        <LASTMODIFYDATE></LASTMODIFYDATE>
        <LEGACY_CKT_ID></LEGACY_CKT_ID>
        <TSP></TSP>
        <A_SIDE_CUSTOMER>STATE OF OHIO</A_SIDE_CUSTOMER>
        <Z_SIDE_CUSTOMER>STATE OF OHIO</Z_SIDE_CUSTOMER>
        <SERVICE_TYPE>COM-EVPL</SERVICE_TYPE>
        <CUSTOMER_PROVIDED_VLAN>3392</CUSTOMER_PROVIDED_VLAN>
        <A_SITE_TYPE>LOCAL</A_SITE_TYPE>
        <Z_SITE_TYPE>LOCAL</Z_SITE_TYPE>
        <A_SITE_ID></A_SITE_ID>
        <Z_SITE_ID></Z_SITE_ID>
        <A_SITE_ADDRESS></A_SITE_ADDRESS>
        <Z_SITE_ADDRESS></Z_SITE_ADDRESS>
    </DATA_DS>
    <DATA_DS>
        <PRM_CID></PRM_CID>
        <PRM_TID>WRRNOHCB1ZW</PRM_TID>
        <CIRCUIT_ID>33.L1XX.000010.210.TWCC</CIRCUIT_ID>
        <REVISION></REVISION>
        <CIRCUIT_STATUS>Live</CIRCUIT_STATUS>
        <BANDWIDTH>25 Mbps</BANDWIDTH>
        <CATEGORY>ETHERNET</CATEGORY>
        <A_SIDE_SITE>WRRNOHCB_STATE OF OHIO/TRUMBULL/280 N PARK AVE</A_SIDE_SITE>
        <Z_SIDE_SITE>CMBROHCO_SOO DEPT JFS/274 HIGHLAND AVE</Z_SIDE_SITE>
        <UTILIZATION></UTILIZATION>
        <BPS_ALLOCATED></BPS_ALLOCATED>
        <IN_SERVICE></IN_SERVICE>
        <Z_CUSTOMER_NAME></Z_CUSTOMER_NAME>
        <TOPOLOGY></TOPOLOGY>
        <ORDERING_CUSTOMER>STATE OF OHIO</ORDERING_CUSTOMER>
        <ADDRESS></ADDRESS>
        <CITY></CITY>
        <STATE></STATE>
        <A_ADDRESS>280 N PARK AVE</A_ADDRESS>
        <A_CITY>WARREN</A_CITY>
        <A_STATE>OH</A_STATE>
        <REPORT_DATE></REPORT_DATE>
        <TID>WRRNOHCB1ZW</TID>
        <LASTMODIFYDATE></LASTMODIFYDATE>
        <LEGACY_CKT_ID></LEGACY_CKT_ID>
        <TSP></TSP>
        <A_SIDE_CUSTOMER>STATE OF OHIO</A_SIDE_CUSTOMER>
        <Z_SIDE_CUSTOMER>STATE OF OHIO</Z_SIDE_CUSTOMER>
        <SERVICE_TYPE>COM-METRO-ETHERNET SERVICES</SERVICE_TYPE>
        <CUSTOMER_PROVIDED_VLAN>3393</CUSTOMER_PROVIDED_VLAN>
        <A_SITE_TYPE>LOCAL</A_SITE_TYPE>
        <Z_SITE_TYPE>LOCAL</Z_SITE_TYPE>
        <A_SITE_ID></A_SITE_ID>
        <Z_SITE_ID></Z_SITE_ID>
        <A_SITE_ADDRESS></A_SITE_ADDRESS>
        <Z_SITE_ADDRESS></Z_SITE_ADDRESS>
    </DATA_DS>
    <DATA_DS>
        <PRM_CID></PRM_CID>
        <PRM_TID>WRRNOHCB1ZW</PRM_TID>
        <CIRCUIT_ID>33.L1XX.000015.210.TWCC</CIRCUIT_ID>
        <REVISION></REVISION>
        <CIRCUIT_STATUS>Live</CIRCUIT_STATUS>
        <BANDWIDTH>10 Mbps</BANDWIDTH>
        <CATEGORY>ETHERNET</CATEGORY>
        <A_SIDE_SITE>WRRNOHCB_STATE OF OHIO/TRUMBULL/280 N PARK AVE</A_SIDE_SITE>
        <Z_SIDE_SITE>CMBROHCP_SOO DEPT JFS//801 E WHEELING AVE</Z_SIDE_SITE>
        <UTILIZATION></UTILIZATION>
        <BPS_ALLOCATED></BPS_ALLOCATED>
        <IN_SERVICE></IN_SERVICE>
        <Z_CUSTOMER_NAME></Z_CUSTOMER_NAME>
        <TOPOLOGY></TOPOLOGY>
        <ORDERING_CUSTOMER>STATE OF OHIO</ORDERING_CUSTOMER>
        <ADDRESS></ADDRESS>
        <CITY></CITY>
        <STATE></STATE>
        <A_ADDRESS>280 N PARK AVE</A_ADDRESS>
        <A_CITY>WARREN</A_CITY>
        <A_STATE>OH</A_STATE>
        <REPORT_DATE></REPORT_DATE>
        <TID>WRRNOHCB1ZW</TID>
        <LASTMODIFYDATE></LASTMODIFYDATE>
        <LEGACY_CKT_ID></LEGACY_CKT_ID>
        <TSP></TSP>
        <A_SIDE_CUSTOMER>STATE OF OHIO</A_SIDE_CUSTOMER>
        <Z_SIDE_CUSTOMER>STATE OF OHIO</Z_SIDE_CUSTOMER>
        <SERVICE_TYPE>COM-METRO-ETHERNET SERVICES</SERVICE_TYPE>
        <CUSTOMER_PROVIDED_VLAN>3394</CUSTOMER_PROVIDED_VLAN>
        <A_SITE_TYPE>LOCAL</A_SITE_TYPE>
        <Z_SITE_TYPE>LOCAL</Z_SITE_TYPE>
        <A_SITE_ID></A_SITE_ID>
        <Z_SITE_ID></Z_SITE_ID>
        <A_SITE_ADDRESS></A_SITE_ADDRESS>
        <Z_SITE_ADDRESS></Z_SITE_ADDRESS>
    </DATA_DS>
    <DATA_DS>
        <PRM_CID></PRM_CID>
        <PRM_TID>WRRNOHCB1ZW</PRM_TID>
        <CIRCUIT_ID>33.L1XX.000024.210.TWCC</CIRCUIT_ID>
        <REVISION></REVISION>
        <CIRCUIT_STATUS>Live</CIRCUIT_STATUS>
        <BANDWIDTH>25 Mbps</BANDWIDTH>
        <CATEGORY>ETHERNET</CATEGORY>
        <A_SIDE_SITE>WRRNOHCB_STATE OF OHIO/TRUMBULL/280 N PARK AVE</A_SIDE_SITE>
        <Z_SIDE_SITE>MLBGOHXB_SOO HOLMES JFS/85 N GRANT ST</Z_SIDE_SITE>
        <UTILIZATION></UTILIZATION>
        <BPS_ALLOCATED></BPS_ALLOCATED>
        <IN_SERVICE></IN_SERVICE>
        <Z_CUSTOMER_NAME></Z_CUSTOMER_NAME>
        <TOPOLOGY></TOPOLOGY>
        <ORDERING_CUSTOMER>STATE OF OHIO</ORDERING_CUSTOMER>
        <ADDRESS></ADDRESS>
        <CITY></CITY>
        <STATE></STATE>
        <A_ADDRESS>280 N PARK AVE</A_ADDRESS>
        <A_CITY>WARREN</A_CITY>
        <A_STATE>OH</A_STATE>
        <REPORT_DATE></REPORT_DATE>
        <TID>WRRNOHCB1ZW</TID>
        <LASTMODIFYDATE></LASTMODIFYDATE>
        <LEGACY_CKT_ID></LEGACY_CKT_ID>
        <TSP></TSP>
        <A_SIDE_CUSTOMER>STATE OF OHIO</A_SIDE_CUSTOMER>
        <Z_SIDE_CUSTOMER>STATE OF OHIO</Z_SIDE_CUSTOMER>
        <SERVICE_TYPE>COM-METRO-ETHERNET SERVICES</SERVICE_TYPE>
        <CUSTOMER_PROVIDED_VLAN>3712</CUSTOMER_PROVIDED_VLAN>
        <A_SITE_TYPE>LOCAL</A_SITE_TYPE>
        <Z_SITE_TYPE>LOCAL</Z_SITE_TYPE>
        <A_SITE_ID></A_SITE_ID>
        <Z_SITE_ID>NEO-SOO HOLMES COUNTY JFS</Z_SITE_ID>
        <A_SITE_ADDRESS></A_SITE_ADDRESS>
        <Z_SITE_ADDRESS></Z_SITE_ADDRESS>
    </DATA_DS>
    <DATA_DS>
        <PRM_CID></PRM_CID>
        <PRM_TID>WRRNOHCB1ZW</PRM_TID>
        <CIRCUIT_ID>33.L1XX.000280..TWCC</CIRCUIT_ID>
        <REVISION></REVISION>
        <CIRCUIT_STATUS>Live</CIRCUIT_STATUS>
        <BANDWIDTH>25 Mbps</BANDWIDTH>
        <CATEGORY>ETHERNET</CATEGORY>
        <A_SIDE_SITE>WRRNOHCB_STATE OF OHIO/TRUMBULL/280 N PARK AVE</A_SIDE_SITE>
        <Z_SIDE_SITE>WRRNOHCQ_SOO JFS//160 HIGH ST NW WARREN</Z_SIDE_SITE>
        <UTILIZATION></UTILIZATION>
        <BPS_ALLOCATED></BPS_ALLOCATED>
        <IN_SERVICE></IN_SERVICE>
        <Z_CUSTOMER_NAME></Z_CUSTOMER_NAME>
        <TOPOLOGY></TOPOLOGY>
        <ORDERING_CUSTOMER>STATE OF OHIO</ORDERING_CUSTOMER>
        <ADDRESS></ADDRESS>
        <CITY></CITY>
        <STATE></STATE>
        <A_ADDRESS>280 N PARK AVE</A_ADDRESS>
        <A_CITY>WARREN</A_CITY>
        <A_STATE>OH</A_STATE>
        <REPORT_DATE></REPORT_DATE>
        <TID>WRRNOHCB1ZW</TID>
        <LASTMODIFYDATE></LASTMODIFYDATE>
        <LEGACY_CKT_ID></LEGACY_CKT_ID>
        <TSP></TSP>
        <A_SIDE_CUSTOMER>STATE OF OHIO</A_SIDE_CUSTOMER>
        <Z_SIDE_CUSTOMER>STATE OF OHIO</Z_SIDE_CUSTOMER>
        <SERVICE_TYPE>COM-METRO-ETHERNET SERVICES</SERVICE_TYPE>
        <CUSTOMER_PROVIDED_VLAN>204</CUSTOMER_PROVIDED_VLAN>
        <A_SITE_TYPE>LOCAL</A_SITE_TYPE>
        <Z_SITE_TYPE>LOCAL</Z_SITE_TYPE>
        <A_SITE_ID></A_SITE_ID>
        <Z_SITE_ID>TRUMBULL COUNTY JAIL</Z_SITE_ID>
        <A_SITE_ADDRESS></A_SITE_ADDRESS>
        <Z_SITE_ADDRESS></Z_SITE_ADDRESS>
    </DATA_DS>
    <DATA_DS>
        <PRM_CID></PRM_CID>
        <PRM_TID>WRRNOHCB1ZW</PRM_TID>
        <CIRCUIT_ID>41001.GE1.WRRNOH551CW.WRRNOHCB1ZW</CIRCUIT_ID>
        <REVISION></REVISION>
        <CIRCUIT_STATUS>Live</CIRCUIT_STATUS>
        <BANDWIDTH>1 Gbps</BANDWIDTH>
        <CATEGORY>ETHERNET TRANSPORT</CATEGORY>
        <A_SIDE_SITE>WRRNOH55_TWC/HUB W1-NILES RD</A_SIDE_SITE>
        <Z_SIDE_SITE>WRRNOHCB_STATE OF OHIO/TRUMBULL/280 N PARK AVE</Z_SIDE_SITE>
        <UTILIZATION></UTILIZATION>
        <BPS_ALLOCATED></BPS_ALLOCATED>
        <IN_SERVICE></IN_SERVICE>
        <Z_CUSTOMER_NAME></Z_CUSTOMER_NAME>
        <TOPOLOGY></TOPOLOGY>
        <ORDERING_CUSTOMER></ORDERING_CUSTOMER>
        <ADDRESS></ADDRESS>
        <CITY></CITY>
        <STATE></STATE>
        <A_ADDRESS>3775 NILES RD SE</A_ADDRESS>
        <A_CITY>WARREN</A_CITY>
        <A_STATE>OH</A_STATE>
        <REPORT_DATE></REPORT_DATE>
        <TID>WRRNOHCB1ZW</TID>
        <LASTMODIFYDATE></LASTMODIFYDATE>
        <LEGACY_CKT_ID></LEGACY_CKT_ID>
        <TSP></TSP>
        <A_SIDE_CUSTOMER></A_SIDE_CUSTOMER>
        <Z_SIDE_CUSTOMER></Z_SIDE_CUSTOMER>
        <SERVICE_TYPE>INT-ACCESS TO PREM TRANSPORT</SERVICE_TYPE>
        <CUSTOMER_PROVIDED_VLAN></CUSTOMER_PROVIDED_VLAN>
        <A_SITE_TYPE>HUB</A_SITE_TYPE>
        <Z_SITE_TYPE>LOCAL</Z_SITE_TYPE>
        <A_SITE_ID>HUB W1-NILES RD</A_SITE_ID>
        <Z_SITE_ID></Z_SITE_ID>
        <A_SITE_ADDRESS></A_SITE_ADDRESS>
        <Z_SITE_ADDRESS></Z_SITE_ADDRESS>
    </DATA_DS>
</circuitDetailss>